regressionresults.py
setup.py
utilsjv.egg-info/PKG-INFO
utilsjv.egg-info/SOURCES.txt
utilsjv.egg-info/dependency_links.txt
utilsjv.egg-info/top_level.txt