Metadata-Version: 1.0
Name: utilsjv
Version: 0.1
Summary: A tiny Python library for DHBW courses
Home-page: https://github.com/microfinance2010
Author: jv
Author-email: UNKNOWN
License: Apache License, Version 2.0
Platform: UNKNOWN
